PredictionIO-0.9.9.dist-info/DESCRIPTION.rst
PredictionIO-0.9.9.dist-info/METADATA
PredictionIO-0.9.9.dist-info/RECORD
PredictionIO-0.9.9.dist-info/WHEEL
PredictionIO-0.9.9.dist-info/metadata.json
PredictionIO-0.9.9.dist-info/top_level.txt
predictionio/__init__.py
predictionio/connection.py
