Metadata-Version: 2.0
Name: PredictionIO
Version: 0.9.9
Summary: PredictionIO Python SDK
Home-page: http://predictionio.apache.org/
Author: Apache PredictionIO
Author-email: user@predictionio.apache.org
License: LICENSE.txt
Platform: UNKNOWN
Classifier: Programming Language :: Python
Classifier: License :: OSI Approved :: Apache Software License
Classifier: Operating System :: OS Independent
Classifier: Development Status :: 4 - Beta
Classifier: Intended Audience :: Developers
Classifier: Intended Audience :: Science/Research
Classifier: Environment :: Web Environment
Classifier: Topic :: Internet :: WWW/HTTP
Classifier: Topic :: Scientific/Engineering :: Artificial Intelligence
Classifier: Topic :: Scientific/Engineering :: Information Analysis
Classifier: Topic :: Software Development :: Libraries :: Python Modules
Requires-Dist: pytz (>=2014.2)
